zscaler_api_talkers/__init__.py
zscaler_api_talkers/client_connector/__init__.py
zscaler_api_talkers/client_connector/talker.py
zscaler_api_talkers/cloud_connector/__init__.py
zscaler_api_talkers/cloud_connector/talker.py
zscaler_api_talkers/helpers/__init__.py
zscaler_api_talkers/helpers/http_calls.py
zscaler_api_talkers/helpers/logger.py
zscaler_api_talkers/helpers/utilities.py
zscaler_api_talkers/zia/__init__.py
zscaler_api_talkers/zia/helpers.py
zscaler_api_talkers/zia/models.py
zscaler_api_talkers/zia/talker.py
zscaler_api_talkers/zpa/__init__.py
zscaler_api_talkers/zpa/talker.py
zscaler_api_talkers-6.4.1.dist-info/LICENSE.txt
zscaler_api_talkers-6.4.1.dist-info/METADATA
zscaler_api_talkers-6.4.1.dist-info/WHEEL
zscaler_api_talkers-6.4.1.dist-info/RECORD
