Metadata-Version: 2.1
Name: zscaler_api_talkers
Version: 6.4.1
Summary: Unofficial Zscaler API python SDK for ZIA, ZPA and Zscaler Client Connector
Author: Sergio Pereira
Author-email: sergitopereira@hotmail.com
Requires-Python: >=3.7
Classifier: Programming Language :: Python :: 3
Classifier: Programming Language :: Python :: 3.7
Classifier: Programming Language :: Python :: 3.8
Classifier: Programming Language :: Python :: 3.9
Classifier: Programming Language :: Python :: 3.10
Classifier: Programming Language :: Python :: 3.11
Classifier: Programming Language :: Python :: 3.12
Requires-Dist: appdirs (>=1.4.4,<2.0.0)
Requires-Dist: requests (>=2.31.0,<3.0.0)
